brainspike/__init__.py
brainspike/abf/__init__.py
brainspike/abf/abf_obj.py
brainspike/abf/data.py
brainspike/abf/metadata.py
brainspike/core/__init__.py
brainspike/core/loader.py
brainspike/core/metadata.py
brainspike/core/ap/__init__.py
brainspike/core/ap/processing.py
brainspike/core/ap/spike_processing.py
brainspike/core/ap/subthreshold_processing.py
brainspike/core/ap/subthreshold/__init__.py
brainspike/core/ap/subthreshold/group_subthreshold_processing.py
brainspike/core/ap/subthreshold/subthreshold_processing.py
brainspike/core/ap/suprathreshold/__init__.py
brainspike/core/ap/suprathreshold/group_spike_processing.py
brainspike/core/ap/suprathreshold/spike_processing.py
brainspike/core/download/__init__.py
brainspike/core/download/database_loader.py
brainspike/core/download/database_metadata.py
brainspike/core/psc/__init__.py
brainspike/core/psc/processing.py
brainspike/curation/__init__.py
brainspike/curation/curationlist.py
brainspike/curation/psc_artefact_checks.py
brainspike/curation/psc_signal_drop.py
brainspike/curation/spike_artefact_checks.py
brainspike/curation/spike_sweepdata_qc.py
brainspike/curation/subthresh_artefact_checks.py
brainspike/curation/subthresh_sweepdata_qc.py
brainspike/download/__init__.py
brainspike/download/allenbrain/__init__.py
brainspike/download/allenbrain/allenbrain_download_utils.py
brainspike/download/allenbrain/allenbrain_obj.py
brainspike/download/allenbrain/data.py
brainspike/download/allenbrain/metadata.py
brainspike/download/allenbrain/query.py
brainspike/download/bardylab/__init__.py
brainspike/download/dandi/__init__.py
brainspike/ephys_scoring/__init__.py
brainspike/ephys_scoring/ephys_dist.py
brainspike/exporters/__init__.py
brainspike/exporters/dataframes.py
brainspike/extractors/__init__.py
brainspike/extractors/psc_extractor.py
brainspike/features/__init__.py
brainspike/features/ap_types.py
brainspike/features/psc_categorization.py
brainspike/features/rheobase.py
brainspike/features/spike_feature_adaptation.py
brainspike-1.0.29.dist-info/LICENSE.txt
brainspike-1.0.29.dist-info/METADATA
brainspike-1.0.29.dist-info/WHEEL
brainspike-1.0.29.dist-info/top_level.txt
brainspike-1.0.29.dist-info/RECORD
