Metadata-Version: 2.1
Name: brainspike
Version: 1.0.29
Summary: Python toolbox for high-throughput patch-clamp analysis
Home-page: https://github.com/bardylab/BrainSpike
Author: Michael Zabolocki, Michael Prasinov, Matthew Prasinov
Author-email: michael.zabolocki@sahmri.com
Keywords: patch-clamp,ephys,intracellular,electrophysiology,action potential
Requires-Python: >=3.8.3, <4
License-File: LICENSE.txt
Requires-Dist: scikit-learn
Requires-Dist: numpy (==1.20.0)
Requires-Dist: BaselineRemoval
Requires-Dist: pyabf
Requires-Dist: allensdk
Requires-Dist: tqdm
